riscv_simenv/SimEnvControl/__init__.py
riscv_simenv/SimEnvControl/admin_cmd/__init__.py
riscv_simenv/SimEnvControl/admin_cmd/add/__init__.py
riscv_simenv/SimEnvControl/admin_cmd/add/app/__init__.py
riscv_simenv/SimEnvControl/admin_cmd/add/app/app_analyze.py
riscv_simenv/SimEnvControl/admin_cmd/add/app/app_register.py
riscv_simenv/SimEnvControl/admin_cmd/add/checkpoint.py
riscv_simenv/SimEnvControl/admin_cmd/add/sysroot.py
riscv_simenv/SimEnvControl/admin_cmd/initrepo.py
riscv_simenv/SimEnvControl/admin_cmd/remove/__init__.py
riscv_simenv/SimEnvControl/admin_cmd/remove/checkpoint.py
riscv_simenv/SimEnvControl/admin_cmd/remove/manifest.py
riscv_simenv/SimEnvControl/admin_cmd/remove/sysroot.py
riscv_simenv/SimEnvControl/admin_cmd/show/__init__.py
riscv_simenv/SimEnvControl/admin_cmd/show/checkpoint.py
riscv_simenv/SimEnvControl/admin_cmd/show/manifest.py
riscv_simenv/SimEnvControl/admin_cmd/show/sysroot.py
riscv_simenv/SimEnvControl/admin_cmd/subrepo.py
riscv_simenv/SimEnvControl/libsimenv/__init__.py
riscv_simenv/SimEnvControl/libsimenv/app_manifest.py
riscv_simenv/SimEnvControl/libsimenv/autocomplete.py
riscv_simenv/SimEnvControl/libsimenv/checkpoints_db.py
riscv_simenv/SimEnvControl/libsimenv/click_bash42_completion.py
riscv_simenv/SimEnvControl/libsimenv/content_manager.py
riscv_simenv/SimEnvControl/libsimenv/manifest_db.py
riscv_simenv/SimEnvControl/libsimenv/repo_path.py
riscv_simenv/SimEnvControl/libsimenv/shcmd_utils.py
riscv_simenv/SimEnvControl/libsimenv/sysroots_db.py
riscv_simenv/SimEnvControl/libsimenv/template_manager/Makefile.template
riscv_simenv/SimEnvControl/libsimenv/template_manager/__init__.py
riscv_simenv/SimEnvControl/libsimenv/template_manager/bootstrap-make-recipes.template
riscv_simenv/SimEnvControl/libsimenv/utils.py
riscv_simenv/SimEnvControl/sim_env_cli.py
riscv_simenv/SimEnvControl/user_cmd/__init__.py
riscv_simenv/SimEnvControl/user_cmd/list.py
riscv_simenv/SimEnvControl/user_cmd/mkgen.py
riscv_simenv/SimEnvControl/user_cmd/spawn.py
riscv_simenv-0.9.0.dist-info/LICENSE
riscv_simenv-0.9.0.dist-info/METADATA
riscv_simenv-0.9.0.dist-info/WHEEL
riscv_simenv-0.9.0.dist-info/entry_points.txt
riscv_simenv-0.9.0.dist-info/RECORD
