Metadata-Version: 2.1
Name: riscv-simenv
Version: 0.9.0
Summary: A tool to reliably pack and spawn a RISC-V workload (app) for simulation.
Home-page: https://github.com/s117/riscv-simenv.git
License: Other/Proprietary License
Keywords: riscv,simenv,anycore
Author: Jiayang Li
Author-email: jli95@ncsu.edu
Requires-Python: >=3.11,<4.0
Classifier: Development Status :: 3 - Alpha
Classifier: License :: Other/Proprietary License
Classifier: Operating System :: POSIX :: Linux
Classifier: Programming Language :: Python :: 3
Classifier: Programming Language :: Python :: 3.11
Classifier: Programming Language :: Python :: 3.12
Classifier: Programming Language :: Python :: 3.13
Requires-Dist: PyYAML (>=6.0.1,<7.0.0)
Requires-Dist: bashlex (>=0.18,<0.19)
Requires-Dist: click (>=8.1.7,<9.0.0)
Requires-Dist: fuzzywuzzy (>=0.18.0,<0.19.0)
Requires-Dist: levenshtein (>=0.26.0,<0.27.0)
Requires-Dist: natsort (>=8.4.0,<9.0.0)
Requires-Dist: pyparsing (>=3.1.2,<4.0.0)
Requires-Dist: tabulate (>=0.9.0,<0.10.0)
Project-URL: Repository, https://github.com/s117/riscv-simenv.git
